simplecm/__init__.py
simplecm/simplecm.py
simplecm-0.1.0.dist-info/WHEEL
simplecm-0.1.0.dist-info/METADATA
simplecm-0.1.0.dist-info/RECORD
